tests/__init__.py
tests/apps.py
tests/models.py
tests/settings.py
tests/test_basemodel.py
tests/test_basemodelwithsoftdelete.py
tests/test_views.py
tests/urls.py
vb_baseapp/__init__.py
vb_baseapp/apps.py
vb_baseapp/context_processors.py
vb_baseapp/storage.py
vb_baseapp/urls.py
vb_baseapp/admin/__init__.py
vb_baseapp/admin/autocomplete_view.py
vb_baseapp/admin/base.py
vb_baseapp/admin/content_type.py
vb_baseapp/admin/log_entry.py
vb_baseapp/admin/permission.py
vb_baseapp/admin/user.py
vb_baseapp/admin/actions/__init__.py
vb_baseapp/admin/actions/basemodel_with_softdelete.py
vb_baseapp/admin/filters/__init__.py
vb_baseapp/admin/filters/log_entry.py
vb_baseapp/admin/utils/__init__.py
vb_baseapp/admin/utils/helper.py
vb_baseapp/admin/widgets/__init__.py
vb_baseapp/admin/widgets/autocomplete.py
vb_baseapp/admin/widgets/image_file.py
vb_baseapp/management/__init__.py
vb_baseapp/management/base.py
vb_baseapp/management/commands/__init__.py
vb_baseapp/management/commands/create_app.py
vb_baseapp/management/commands/create_custom_user_model.py
vb_baseapp/management/commands/create_model.py
vb_baseapp/management/template_structures/__init__.py
vb_baseapp/management/template_structures/admins/__init__.py
vb_baseapp/management/template_structures/admins/basemodel.py
vb_baseapp/management/template_structures/admins/custom_user.py
vb_baseapp/management/template_structures/admins/django.py
vb_baseapp/management/template_structures/admins/softdelete.py
vb_baseapp/management/template_structures/application/__init__.py
vb_baseapp/management/template_structures/application/apps.py
vb_baseapp/management/template_structures/application/html.py
vb_baseapp/management/template_structures/application/tests.py
vb_baseapp/management/template_structures/application/urls.py
vb_baseapp/management/template_structures/application/views.py
vb_baseapp/management/template_structures/forms/__init__.py
vb_baseapp/management/template_structures/forms/custom_user.py
django_vb_baseapp-1.1.12.dist-info/LICENCE
django_vb_baseapp-1.1.12.dist-info/METADATA
django_vb_baseapp-1.1.12.dist-info/WHEEL
django_vb_baseapp-1.1.12.dist-info/top_level.txt
django_vb_baseapp-1.1.12.dist-info/RECORD
