Metadata-Version: 2.1
Name: django-vb-baseapp
Version: 1.1.12
Summary: Magical app for django-vb-admin
Home-page: https://github.com/vbyazilim/django-vb-baseapp
Author: vb YAZILIM
Author-email: hello@vbyazilim.com
License: MIT
Platform: UNKNOWN
Classifier: Development Status :: 4 - Beta
Classifier: Environment :: Web Environment
Classifier: Framework :: Django
Classifier: Framework :: Django :: 2.2
Classifier: Intended Audience :: Developers
Classifier: License :: OSI Approved :: MIT License
Classifier: Operating System :: OS Independent
Classifier: Programming Language :: Python :: 3.6
Classifier: Programming Language :: Python :: 3 :: Only
Classifier: Topic :: Internet :: WWW/HTTP
Classifier: Topic :: Internet :: WWW/HTTP :: Dynamic Content
Requires-Python: >=3.6
Requires-Dist: vb-console
